raphaelpy/__init__.py
raphaelpy/defs.py
raphaelpy/element.py
raphaelpy/paper.py
raphaelpy/raphael.py
raphaelpy/set.py
raphaelpy/utils.py
raphaelpy-0.2.0.dist-info/LICENSE
raphaelpy-0.2.0.dist-info/METADATA
raphaelpy-0.2.0.dist-info/WHEEL
raphaelpy-0.2.0.dist-info/top_level.txt
raphaelpy-0.2.0.dist-info/RECORD
