Metadata-Version: 2.1
Name: raphaelpy
Version: 0.2.0
Summary: Library for creating SVG drawings using Python, inspired by RaphaëlJS
Home-page: https://github.com/stranskyjan/raphaelpy
Author: Jan Stransky
Author-email: honzik.stransky@gmail.com
License: LGPL
Keywords: Python SVG RaphaelJS Raphael
Platform: UNKNOWN
Classifier: Development Status :: 4 - Beta
Classifier: License :: OSI Approved :: GNU Lesser General Public License v3 (LGPLv3)
Classifier: Programming Language :: Python
Classifier: Programming Language :: Python :: 2
Classifier: Programming Language :: Python :: 3
Classifier: Operating System :: OS Independent
